{
    "比特幣": [
        "比特幣走勢",
        "比特幣怎麼玩",
        "比特幣價格",
        "比特幣美金",
        "比特幣是什麼",
        "比特幣走勢圖",
        "比特幣怎麼買",
        "比特幣詐騙"
    ],
    "比特幣價格": [
        "比特幣價格走勢",
        "比特幣價格美元",
        "比特幣價格台幣",
        "一顆比特幣價格",
        "比特幣價格歷史",
        "比特幣美金",
        "比特幣10年走勢",
        "比特幣怎麼玩",
        "財經",
        "購物",
        "台幣",
        "美元",
        "走勢",
        "一 顆",
        "歷史"
    ],
    "比特幣怎麼玩": [
        "投資比特幣安全嗎",
        "比特幣怎麼買台灣",
        "比特幣怎麼玩dcard",
        "比特幣投資詐騙",
        "比特幣怎麼挖",
        "比特幣怎麼玩ptt",
        "比特幣投資教學",
        "比特幣賺錢ptt"
    ],
    "比特幣怎麼買": [
        "7-11買比特幣",
        "比特幣怎麼買台灣",
        "比特幣怎麼買dcard",
        "買比特幣要多少錢",
        "比特幣台灣銀行",
        "買bitcoin香港",
        "比特幣怎麼買賣",
        "比特幣交易平台推薦"
    ],
    "比特幣是什麼": [
        "比特幣可以幹嘛",
        "比特幣挖礦原理",
        "比特幣怎麼玩",
        "比特幣詐騙",
        "比特幣可以換現金嗎",
        "比特幣價格",
        "比特幣是哪個國家的",
        "投資比特幣安全嗎"
    ],
    "比特幣美金": [
        "比特幣美金走勢",
        "比特幣10年走勢",
        "比特幣價格美元",
        "比特幣台幣",
        "一顆比特幣價格",
        "比特幣走勢",
        "比特幣怎麼玩",
        "比特幣新聞",
        "財經",
        "購物"
    ],
    "比特幣詐騙": [
        "比特幣詐騙交友",
        "比特幣詐騙平台",
        "比特幣詐騙ptt",
        "虛擬貨幣詐騙錢拿的回來嗎",
        "比特幣詐騙集團",
        "line比特幣詐騙",
        "投資比特幣詐騙",
        "虛擬貨幣詐騙交友",
        "購物",
        "交友",
        "平台",
        "Ptt",
        "詐騙 集團",
        "Line"
    ],
    "比特幣走勢": [
        "比特幣10年走勢",
        "比特幣走勢圖",
        "比特幣走勢預測",
        "比特幣價格",
        "比特幣美金",
        "比特幣新聞",
        "比特幣價格美元",
        "比特幣概念股",
        "走勢 圖"
    ],
    "比特幣走勢圖": [
        "比特幣10年走勢",
        "比特幣價格",
        "比特幣走勢預測",
        "比特幣概念股",
        "比特幣歷史價格走勢",
        "比特幣etf",
        "比特幣價格歷史",
        "比特幣價格美元",
        "購物"
    ],
    "7-11買比特幣": [
        "買比特幣要多少錢",
        "購買比特幣流程",
        "全家買比特幣ptt",
        "賣比特幣",
        "虛擬貨幣實體店面",
        "比特幣怎麼買台灣",
        "全家比特幣",
        "幣安實體店面",
        "購物"
    ],
    "line比特幣詐騙": [
        "比特幣詐騙交友",
        "比特幣詐騙平台",
        "比特幣詐騙手法",
        "比特幣詐騙dcard",
        "比特幣詐騙ptt",
        "虛擬貨幣詐騙錢拿的回來嗎",
        "比特幣詐騙新聞",
        "虛擬貨幣詐騙交友"
    ],
    "一顆比特幣價格": [
        "比特幣一顆多少台幣",
        "比特幣價格美元",
        "比特幣怎麼玩",
        "比特幣10年走勢",
        "比特幣價格歷史",
        "比特幣美金",
        "比特幣價格走勢",
        "比特幣詐騙"
    ],
    "以太幣走勢": [
        "以太幣走勢預測",
        "以太幣最新消息",
        "以太幣會漲到多少",
        "比特幣",
        "以太幣走勢圖",
        "以太幣詐騙",
        "以太幣怎麼玩",
        "以太幣暴跌",
        "購物",
        "預測",
        "圖",
        "分析"
    ],
    "台幣": [
        "台幣匯率",
        "台幣汇率人民币",
        "台幣匯率走勢",
        "台幣美金",
        "美金台幣走勢",
        "新台幣匯率",
        "美金台幣匯率",
        "台幣英文"
    ],
    "投資比特幣安全嗎": [
        "投資比特幣詐騙",
        "比特幣台灣合法嗎",
        "比特幣可以換現金嗎",
        "比特幣詐騙交友",
        "比特幣投資平台",
        "比特幣怎麼玩",
        "比特幣缺點",
        "比特幣可以幹嘛"
    ],
    "投資比特幣詐騙": [
        "比特幣詐騙交友",
        "比特幣詐騙ptt",
        "比特幣詐騙平台",
        "投資比特幣安全嗎",
        "虛擬貨幣詐騙錢拿的回來嗎",
        "比特幣詐騙集團",
        "比特幣詐騙新聞",
        "比特幣詐騙dcard",
        "購物"
    ],
    "比特幣10年走勢": [
        "比特幣歷史價格走勢",
        "比特幣10年走勢圖",
        "比特幣最低價格",
        "比特幣歷年價格",
        "比特幣歷史高位",
        "比特幣歷史最低價格",
        "比特幣歷史最高價",
        "比特幣走勢",
        "圖"
    ],
    "比特幣etf": [
        "比特幣etf台灣",
        "比特幣etf美股",
        "比特幣etf代號",
        "比特幣etf走勢",
        "比特幣etf比較",
        "比特幣etf推薦",
        "比特幣etf怎麼買",
        "比特幣etf購買"
    ],
    "比特幣交易平台推薦": [
        "比特幣交易平台推薦ptt",
        "台灣比特幣交易平台",
        "台灣合法虛擬貨幣交易所",
        "虛擬貨幣交易所詐騙",
        "虛擬貨幣交易平台",
        "台灣虛擬貨幣交易所排名",
        "台灣虛擬貨幣交易所ptt",
        "比特幣台灣合法"
    ],
    "比特幣價格台幣": [
        "1000比特幣等於台幣多少",
        "一顆比特幣價格",
        "比特幣換算美金",
        "1比特幣等於美金多少",
        "比特幣價格美元",
        "5000台幣比特幣",
        "比特幣怎麼玩",
        "比特幣怎麼買"
    ],
    "比特幣價格歷史": [
        "   比特幣十年走勢    ",
        "   比特幣歷史最低價格    ",
        "   比特幣歷史價格走勢    ",
        "   比特幣歷年價格    ",
        "   比特幣10年前價格    ",
        "   比特幣歷史高位    ",
        "   比特幣最早價格    ",
        "   比特幣歷史最高價    "
    ],
    "比特幣價格美元": [
        "比特幣價格走勢",
        "一顆比特幣價格",
        "比特幣10年走勢",
        "BTC/USD",
        "比特幣歷史價格走勢",
        "比特幣價格歷史",
        "比特幣怎麼玩",
        "比特幣價格台幣",
        "財經",
        "購物"
    ],
    "比特幣價格走勢": [
        "比特幣10年走勢",
        "比特幣價格美元",
        "比特幣歷史價格走勢",
        "比特幣價格歷史",
        "一顆比特幣價格",
        "比特幣走勢圖",
        "比特幣走勢預測",
        "比特幣美金"
    ],
    "比特幣可以幹嘛": [
        "比特幣可以換現金嗎",
        "比特幣挖礦原理",
        "比特幣價格",
        "比特幣詐騙",
        "比特幣怎麼玩",
        "投資比特幣安全嗎",
        "比特幣可以買什麼",
        "比特幣走勢"
    ],
    "比特幣可以換現金嗎": [
        "比特幣一顆多少台幣",
        "比特幣換現金台灣",
        "比特幣換現金ptt",
        "比特幣可以幹嘛",
        "比特幣詐騙",
        "投資比特幣安全嗎",
        "比特幣台灣合法嗎",
        "比特幣可以買什麼"
    ],
    "比特幣台幣": [
        "1000比特幣等於台幣多少",
        "5000台幣比特幣",
        "一個比特幣多少錢",
        "一比特幣等於多少美金",
        "比特幣台幣走勢",
        "比特幣換算美金",
        "比特幣換台幣ptt",
        "比特幣換台幣手續費",
        "財經",
        "走勢"
    ],
    "比特幣台灣銀行": [
        "比特幣台灣交易所",
        "7-11買比特幣",
        "比特幣台灣合法",
        "比特幣自動櫃員機地點",
        "比特幣atm領錢",
        "台灣比特幣atm機",
        "比特幣atm教學",
        "買比特幣要多少錢"
    ],
    "比特幣怎麼挖": [],
    "比特幣怎麼玩dcard": [
        "虛擬貨幣慘賠dcard",
        "比特幣 賺錢 Dcard",
        "比特幣怎麼買dcard",
        "比特幣入門dcard",
        "比特幣dcard",
        "幣圈詐騙dcard",
        "Dcard 幣圈",
        "比特幣價格",
        "購物"
    ],
    "比特幣怎麼玩ptt": [
        "比特幣致富ptt",
        "比特幣 自動 交易 ptt",
        "虛擬貨幣 看 盤 PTT",
        "SOL幣 PTT",
        "比特幣賺錢 PTT",
        "比特幣 大 跌 PTT",
        "比特幣價格 PTT",
        "虛擬貨幣技術分析PTT",
        "購物"
    ],
    "比特幣怎麼買dcard": [
        "比特幣入門dcard",
        "虛擬貨幣慘賠dcard",
        "比特幣 賺錢 Dcard",
        "7-11買比特幣",
        "比特幣價格",
        "比特幣怎麼玩",
        "加密貨幣dcard",
        "比特幣ptt",
        "購物"
    ],
    "比特幣怎麼買台灣": [
        "7-11買比特幣",
        "比特幣怎麼買dcard",
        "買比特幣要多少錢",
        "比特幣台灣銀行",
        "比特幣台灣合法",
        "比特幣怎麼買賣",
        "台灣比特幣etf",
        "買比特幣詐騙"
    ],
    "比特幣怎麼買賣": [
        "7-11買比特幣",
        "比特幣怎麼買dcard",
        "比特幣怎麼買台灣",
        "比特幣交易平台推薦",
        "比特幣台灣銀行",
        "比特幣可以買什麼",
        "買bitcoin犯法",
        "買比特幣要多少錢"
    ],
    "比特幣投資教學": [
        "比特幣投資詐騙",
        "7-11買比特幣",
        "比特幣價格",
        "比特幣投資ptt",
        "比特幣怎麼買dcard",
        "比特幣 台灣銀行",
        "比特幣怎麼買台灣",
        "比特幣投資平台"
    ],
    "比特幣投資詐騙": [
        "比特幣詐騙交友",
        "虛擬貨幣詐騙錢拿的回來嗎",
        "line比特幣詐騙",
        "虛擬貨幣詐騙交友",
        "比特幣詐騙ptt",
        "比特幣詐騙集團",
        "比特幣詐騙平台",
        "比特幣詐騙新聞",
        "購物"
    ],
    "比特幣挖礦原理": [
        "1比特幣挖多久",
        "比特幣挖礦原理ptt",
        "挖礦賺錢原理",
        "比特幣可以幹嘛",
        "挖礦合法嗎",
        "虛擬貨幣挖礦原理",
        "比特幣挖礦教學",
        "比特幣挖礦成本"
    ],
    "比特幣新聞": [
        "比特幣新聞即時",
        "比特幣新聞狂人",
        "台灣比特幣新聞",
        "比特幣即時走勢",
        "比特幣走勢預測",
        "比特幣詐騙新聞",
        "比特幣10年走勢",
        "比特幣價格"
    ],
    "比特幣是哪個國家的": [
        "比特幣詐騙",
        "比特幣價格",
        "比特幣是什麼",
        "比特幣挖礦原理",
        "比特幣可以換現金嗎",
        "比特幣走勢",
        "比特幣可以幹嘛",
        "比特幣歷史價格"
    ],
    "比特幣概念股": [
        "比特幣概念股ptt",
        "比特幣概念股台股",
        "比特幣概念股美股",
        "比特幣概念股3443",
        "比特幣股票代號",
        "比特幣股票有哪些",
        "台灣有哪些虛擬貨幣概念股",
        "台股比特幣etf"
    ],
    "比特幣歷史價格走勢": [
        "比特幣十年走勢",
        "比特幣歷史最低價格",
        "比特幣歷年價格",
        "比特幣10年前價格",
        "比特幣歷史高位",
        "比特幣歷史最高價",
        "比特幣走勢預測2023",
        "比特幣價格走勢"
    ],
    "比特幣美金走勢": [
        "比特幣10年走勢",
        "比特幣價格美元",
        "比特幣走勢",
        "比特幣歷史價格走勢",
        "比特幣詐騙",
        "BTC/USD",
        "一顆比特幣價格",
        "比特幣走勢預測",
        "購物"
    ],
    "比特幣詐騙ptt": [
        "幣安詐騙dcard",
        "虛擬貨幣詐騙交友",
        "火幣詐騙 PTT",
        "比特幣致富 PTT",
        "以太幣詐騙ptt",
        "虛擬貨幣洗錢ptt",
        "泰達幣詐騙 PTT",
        "外匯詐騙PTT",
        "購物"
    ],
    "比特幣詐騙交友": [
        "比特幣詐騙手法",
        "line比特幣詐騙",
        "比特幣詐騙dcard",
        "比特幣詐騙ptt",
        "虛擬貨幣詐騙錢拿的回來嗎",
        "交友軟體usdt詐騙",
        "比特幣詐騙新聞",
        "比特幣詐騙平台"
    ],
    "比特幣詐騙平台": [
        "比特幣詐騙交友",
        "虛擬貨幣詐騙錢拿的回來嗎",
        "line比特幣詐騙",
        "假交易所詐騙",
        "投資比特幣詐騙",
        "比特幣詐騙ptt",
        "比特幣詐騙dcard",
        "虛擬貨幣詐騙交友"
    ],
    "比特幣詐騙集團": [
        "比特幣詐騙交友",
        "比特幣詐騙平台",
        "line比特幣詐騙",
        "比特幣詐騙新聞",
        "比特幣詐騙dcard",
        "虛擬貨幣詐騙錢拿的回來嗎",
        "比特幣詐騙ptt",
        "虛擬貨幣詐騙交友"
    ],
    "比特幣賺錢ptt": [
        "比特幣致富 PTT",
        "比特幣價格 PTT",
        "SOL幣 PTT",
        "幣安 賺幣 PTT",
        "以太幣 PTT",
        "比特幣 當沖 PTT",
        "比特幣 賠錢 PTT",
        "比特幣 開戶 ptt",
        "購物"
    ],
    "比特幣走勢預測": [
        "比特幣新聞即時",
        "比特幣走勢預測2024",
        "比特幣還可以買嗎",
        "比特幣2024預測",
        "比特幣走勢分析",
        "比特幣走勢圖",
        "比特幣10年走勢",
        "比特幣走勢預測2023"
    ],
    "美元": [
        "美元走勢",
        "美元匯率",
        "美元人民币",
        "美元指數",
        "美元台幣",
        "美元兌台幣未來走勢",
        "美元兌日圓",
        "美元匯率走勢圖"
    ],
    "虛擬貨幣詐騙交友": [
        "虛擬貨幣詐騙dcard",
        "虛擬貨幣詐騙錢拿的回來嗎",
        "比特幣詐騙交友",
        "交友軟體usdt詐騙",
        "虛擬貨幣詐騙ptt",
        "虛擬貨幣詐騙案例",
        "usdt愛情詐騙",
        "幣安愛情詐騙"
    ],
    "虛擬貨幣詐騙錢拿的回來嗎": [
        "詐騙拿回錢的機率ptt",
        "虛擬貨幣帳戶凍結",
        "虛擬貨幣詐騙ptt",
        "虛擬貨幣詐騙自救",
        "虛擬貨幣詐騙dcard",
        "被詐騙錢拿的回來嗎dcard",
        "虛擬貨幣詐騙交友",
        "投資詐騙錢拿的回來嗎"
    ],
    "財經": [
        "財經google",
        "財經股市",
        "財經系",
        "財經英文",
        "財經是什麼",
        "財經新聞",
        "財經網站",
        "財經新聞快報"
    ],
    "買bitcoin香港": [
        "買bitcoin犯法",
        "比特幣交易平台推薦香港",
        "香港比特幣倒閉",
        "買bitcoin lihkg",
        "比特幣香港合法",
        "買比特幣平台",
        "香港比特幣提款機",
        "香港虛擬貨幣交易所排名"
    ],
    "買比特幣要多少錢": [
        "7-11買比特幣",
        "比特幣一顆多少台幣",
        "比特幣價格",
        "比特幣走勢",
        "幣安"
    ],
    "購物": [
        "蝦皮購物",
        "momo購物",
        "東森購物",
        "yahoo購物",
        "momo購物電話",
        "pchome 24h購物",
        "pchome購物",
        "蝦皮購物網站",
        "購物",
        "營業中",
        "蝦皮 購物",
        "Momo 購物",
        "東森 購物",
        "Yahoo"
    ],
    "走勢": [
        "台股大盤走勢圖",
        "台股大盤歷史走勢圖",
        "今日股市大盤",
        "美股走勢分析",
        "台股大盤指數",
        "台股十年走勢圖",
        "今日股市漲跌",
        "今日股市大跌原因",
        "購物"
    ],
    "1000比特幣等於台幣多少": [
        "一個比特幣多少錢",
        "5000台幣比特幣",
        "1比特幣等於美金多少",
        "一元比特幣等於台幣多少",
        "1比特幣挖多久",
        "比特幣換算美金",
        "比特幣換現金",
        "比特幣換台幣手續費",
        "財經"
    ],
    "1比特幣挖多久": [
        "1比特幣挖多久ptt",
        "1比特幣等於多少台幣",
        "手機挖比特幣",
        "比特幣挖礦程式",
        "手機挖礦",
        "比特幣挖礦app",
        "比特幣挖礦程式下載",
        "比特幣挖礦成本"
    ],
    "1比特幣等於美金多少": [
        "1比特幣等於台幣多少",
        "比特幣換算美金",
        "1000比特幣等於台幣多少",
        "一顆比特幣價格",
        "比特幣怎麼玩",
        "比特幣價格美元",
        "比特幣美金走勢",
        "比特幣詐騙"
    ],
    "5000台幣比特幣": [
        "一元比特幣等於台幣多少",
        "1000比特幣等於台幣多少",
        "一個比特幣多少錢",
        "一比特幣等於多少美金",
        "比特幣換現金",
        "比特幣換台幣手續費",
        "比特幣換台幣ptt",
        "比特幣台幣走勢",
        "財經",
        "購物"
    ],
    "BTC/USD": [
        "bitcoin價格usd",
        "btc走勢",
        "btc行情",
        "比特幣美金走勢",
        "比特幣10年走勢",
        "比特幣詐騙",
        "btc是什麼",
        "一顆比特幣價格",
        "財經"
    ],
    "Dcard 幣圈": [
        "幣圈ptt",
        "虛擬貨幣慘賠dcard",
        "幣圈詐騙dcard",
        "幣圈 Alex Dcard",
        "虛擬貨幣dcard",
        "幣圈新手 Dcard",
        "虛擬貨幣賺錢dcard",
        "股票跟虛擬貨幣dcard",
        "購物"
    ],
    "Line": [
        "line電腦版",
        "line網頁版",
        "line下載",
        "官方line下載",
        "line登入",
        "line下載安卓",
        "line更新",
        "line官方"
    ],
    "Ptt": [
        "ptt网页版",
        "ptt八卦版",
        "ptt登入",
        "ptt註冊",
        "ptt電腦版",
        "ptt熱門",
        "ptt掛了",
        "ptt是什麼",
        "八卦 版",
        "网页 版",
        "登入"
    ],
    "SOL幣 PTT": [
        "以太幣 PTT",
        "比特幣致富 PTT",
        "SUI 幣 ptt",
        "KAS幣 ptt",
        "幣安PTT",
        "sol幣目標價",
        "sol幣新聞",
        "幣安 賺幣 PTT"
    ],
    "momo購物": [
        "   momo購物網客服    ",
        "   東森購物    ",
        "   momo登入    ",
        "   momo購物電話    ",
        "   momo購物型錄    ",
        "   momo購物客服電話    ",
        "   momo電視購物    ",
        "   pchome購物    ",
        "購物",
        "客服"
    ],
    "momo購物電話": [
        "momo真人客服",
        "momo電話客服080",
        "momo免付費電話",
        "momo客服電話02",
        "momo會員中心電話",
        "momo電話號碼",
        "momo客服24小時嗎",
        "momo購物網客服電話真人ptt"
    ],
    "pchome 24h購物": [
        "pchome 24h到貨時間",
        "pchome購物",
        "PChome",
        "momo購物",
        "pchome商店街",
        "pchome 24h購物客服",
        "pchome 24h購物客服電話0800",
        "pchome 24h到貨規則",
        "購物"
    ],
    "pchome購物": [
        "pchome商店街",
        "momo購物",
        "pchome 24h購物",
        "pchome首頁",
        "Momo",
        "PChome",
        "pchome 24h到貨時間",
        "東森購物",
        "購物"
    ],
    "usdt愛情詐騙": [
        "交友軟體usdt詐騙",
        "usdt詐騙手法",
        "usdt詐騙dcard",
        "虛擬貨幣詐騙交友",
        "line感情詐騙",
        "虛擬貨幣 戀愛 詐騙",
        "usdt是什麼",
        "幣安usdt詐騙"
    ],
    "yahoo購物": [
        "yahoo拍賣",
        "yahoo首頁",
        "yahoo購物登入",
        "yahoo購物中心電腦版",
        "Yahoo jp",
        "yahoo購物訂單查詢",
        "yahoo購物免運",
        "yahoo購物中心正品",
        "購物",
        "登入",
        "中心 電腦 版",
        "訂單 查詢",
        "免 運",
        "購物 中心 正品"
    ],
    "一個比特幣多少錢": [
        "比特幣一顆多少台幣",
        "一比特幣等於多少美金",
        "比特幣價格美元",
        "1000比特幣等於台幣多少",
        "比特幣怎麼玩",
        "比特幣詐騙",
        "比特幣價格走勢",
        "比特幣怎麼買"
    ],
    "一比特幣等於多少美金": [
        "一比特幣等於多少台幣",
        "比特幣換算美金",
        "比特幣 一 枚 多少 錢",
        "1000比特幣等於台幣多少",
        "比特幣價格美元",
        "比特幣怎麼玩",
        "比特幣美金走勢",
        "比特幣新聞"
    ],
    "交友": [
        "交友軟體免費",
        "交友網頁",
        "交友軟體推薦dcard",
        "交友軟體心得",
        "單身交友網站",
        "台灣交友網站",
        "正經交友app",
        "交友軟體dcard"
    ],
    "交友軟體usdt詐騙": [
        "usdt愛情詐騙",
        "usdt詐騙手法",
        "usdt詐騙dcard",
        "usdt詐騙ptt",
        "usdt挖礦詐騙",
        "幣安usdt詐騙",
        "交友軟體詐騙套路",
        "幣安詐騙交友",
        "購物"
    ],
    "人民幣台幣": [
        "人民幣台幣走勢",
        "美金台幣",
        "人民幣匯率",
        "人民幣台幣台灣銀行",
        "台幣換人民幣划算",
        "1元人民幣等於多少台幣",
        "人民幣換算",
        "100人民幣等於多少台幣",
        "財經",
        "走勢"
    ],
    "以太幣 PTT": [
        "   比特幣致富ptt    ",
        "   萊特幣 PTT    ",
        "   比特幣崩盤ptt    ",
        "   以太幣2024    ",
        "   虛擬貨幣入門ptt    ",
        "   加密貨幣未來ptt    ",
        "   比特幣價格 PTT    ",
        "   Cyber 幣 ptt    ",
        "購物"
    ],
    "以太幣怎麼玩": [
        "以太幣怎麼挖",
        "以太幣投資教學",
        "以太幣詐騙",
        "以太幣投資ptt",
        "以太幣未來趨勢",
        "以太幣未來趨勢ptt",
        "以太幣交易平台推薦",
        "以太幣值得投資嗎"
    ],
    "以太幣暴跌": [
        "以太幣最新消息",
        "以太幣值得投資嗎",
        "以太幣未來趨勢",
        "以太幣走勢",
        "以太幣未來趨勢2024",
        "以太幣即時",
        "以太幣新聞",
        "以太幣會漲到多少"
    ],
    "以太幣最新消息": [
        "比特幣最新消息",
        "以太幣未來趨勢2023",
        "以太幣會漲到多少",
        "以太幣暴跌",
        "以太幣新聞",
        "以太幣即時",
        "以太幣走勢",
        "以太幣怎麼玩"
    ],
    "以太幣會漲到多少": [
        "以太幣值得投資嗎",
        "以太幣最新消息",
        "以太幣未來趨勢ptt",
        "以太幣2024",
        "以太幣未來趨勢2024",
        "以太幣目標價",
        "以太幣新聞",
        "以太幣2030"
    ],
    "以太幣詐騙": [],
    "以太幣詐騙ptt": [
        "以太幣ptt",
        "XRP幣 ptt",
        "購物"
    ],
    "以太幣走勢圖": [
        "以太幣暴跌",
        "以太幣未來趨勢",
        "以太幣價格",
        "比特幣",
        "以太幣怎麼玩",
        "以太幣台幣走勢",
        "以太幣最新消息",
        "乙太幣匯率"
    ],
    "以太幣走勢預測": [
        "以太幣最新消息",
        "以太幣會漲到多少",
        "以太幣未來趨勢2024",
        "以太幣未來趨勢ptt",
        "以太幣值得投資嗎",
        "以太幣目標價",
        "以太幣暴跌",
        "以太幣2024"
    ],
    "假交易所詐騙": [
        "交易平台詐騙",
        "詐騙交易所查詢",
        "國際交易平台詐騙",
        "虛擬貨幣詐騙交友",
        "Bit 交易所詐騙",
        "max交易所詐騙手法",
        "trcoex交易所詐騙",
        "虛擬貨幣詐騙自救"
    ],
    "全家比特幣": [
        "全家比特幣賣出",
        "全家比特幣ptt",
        "全家買比特幣",
        "7-11買比特幣",
        "比特幣怎麼買dcard",
        "購買比特幣流程",
        "比特幣價格",
        "全家幣託",
        "購物",
        "賣 出"
    ],
    "全家買比特幣ptt": [],
    "分析": [
        "分析英語",
        "分析意思",
        "分析google",
        "分析英文名詞",
        "分析analysis",
        "分析定義",
        "分析方式",
        "分析名詞"
    ],
    "加密貨幣dcard": [
        "虛擬貨幣慘賠dcard",
        "加密貨幣入門 Dcard",
        "瘋男加密貨幣dcard",
        "虛擬貨幣心得ptt",
        "加密貨幣ptt",
        "加密貨幣怎麼玩",
        "虛擬貨幣賺錢dcard",
        "加密貨幣詐騙dcard",
        "瘋 男"
    ],
    "台幣匯率": [
        "美金台幣匯率",
        "台幣匯率走勢",
        "美金匯率",
        "日幣匯率",
        "匯率查詢",
        "台幣匯率走勢即時",
        "人民幣匯率",
        "台灣銀行匯率",
        "財經",
        "購物",
        "美金",
        "走勢",
        "人民幣",
        "港幣"
    ],
    "台幣匯率走勢": [
        "今日台幣匯率走勢",
        "台幣美金匯率走勢",
        "美元兌台幣未來走勢",
        "今日台幣匯率走勢圖",
        "美金匯率走勢預測",
        "1美金換台幣",
        "美元匯率走勢圖",
        "美金匯率走勢圖十年",
        "今日",
        "購物"
    ],
    "台幣美金": [
        "1美金換台幣",
        "台幣美金匯率",
        "台幣美金匯率走勢",
        "台幣匯率",
        "人民幣台幣",
        "美元兌台幣未來走勢",
        "1000美金換台幣多少",
        "台灣銀行美金匯率",
        "財經"
    ],
    "台灣合法虛擬貨幣交易所": [
        "台灣虛擬貨幣交易所排名",
        "虛擬貨幣交易所詐騙",
        "台灣虛擬貨幣交易所ptt",
        "台灣三大交易所",
        "台灣合法加密貨幣交易所",
        "台灣虛擬貨幣交易所倒閉",
        "台灣虛擬貨幣交易所推薦",
        "max交易所"
    ],
    "台灣挖礦犯法嗎": [
        "挖礦賺錢原理",
        "挖礦風險",
        "挖礦詐騙",
        "挖礦電費",
        "挖礦機",
        "挖礦違法",
        "免費挖礦",
        "挖礦是什麼"
    ],
    "台灣有哪些虛擬貨幣概念股": [
        "比特幣概念股3443",
        "比特幣概念股ptt",
        "比特幣股票代號",
        "區塊鏈概念股台灣",
        "鋰礦概念股台灣",
        "比特幣概念股是什麼",
        "挖礦概念股",
        "加密貨幣概念股美股"
    ],
    "台灣比特幣atm機": [
        "比特幣atm詐騙",
        "比特幣自動櫃員機地點",
        "比特幣atm教學",
        "比特幣atm台北",
        "台北比特幣旗艦店",
        "比特幣atm領錢",
        "比特幣atm地圖",
        "比特幣atm高雄"
    ],
    "台灣比特幣etf": [],
    "台灣比特幣交易平台": [
        "比特幣台灣銀行",
        "比特幣台灣合法",
        "比特幣交易平台推薦",
        "台灣合法虛擬貨幣交易所",
        "比特幣交易平台推薦ptt",
        "台灣虛擬貨幣交易所排名",
        "7-11買比特幣",
        "虛擬貨幣交易所詐騙"
    ],
    "台灣比特幣新聞": [
        "比特幣新聞即時",
        "比特幣詐騙新聞",
        "比特幣暴跌",
        "比特幣 新聞 狂人",
        "虛擬貨幣即時新聞",
        "比特幣走勢",
        "虛擬幣 新聞",
        "比特幣價格"
    ],
    "台灣虛擬貨幣交易所ptt": [
        "台灣虛擬貨幣交易所排名",
        "虛擬貨幣交易所dcard",
        "台灣合法虛擬貨幣交易所",
        "台灣三大交易所",
        "max交易所ptt",
        "weex交易所ptt",
        "台灣四大交易所",
        "台灣虛擬貨幣交易所max",
        "購物"
    ],
    "台灣虛擬貨幣交易所排名": [
        "虛擬貨幣交易所詐騙",
        "台灣虛擬貨幣交易所ptt",
        "台灣虛擬貨幣交易所倒閉",
        "台灣三大交易所",
        "台灣虛擬貨幣交易所推薦",
        "台灣虛擬貨幣合法嗎",
        "全球交易所排名",
        "台灣四大交易所"
    ],
    "台股比特幣etf": [
        "比特幣etf台灣",
        "台灣比特幣etf",
        "比特幣etf有哪些",
        "比特幣etf代號",
        "比特幣etf推薦",
        "比特幣etf走勢",
        "比特幣etf怎麼買",
        "比特幣etf比較"
    ],
    "圖": [
        "圖意思",
        "圖搜圖",
        "圖字",
        "圖筆順",
        "圖造詞"
    ],
    "外匯詐騙PTT": [
        "外匯詐騙dcard",
        "外匯代操ptt",
        "外匯保證金詐騙",
        "外匯 保證金 詐騙 PTT",
        "外匯交易平台ptt",
        "炒外匯詐騙",
        "外匯課程 詐騙",
        "XM 外匯 ptt"
    ],
    "幣圈詐騙dcard": [
        "虛擬貨幣詐騙交友dcard",
        "usdt詐騙dcard",
        "max交易所詐騙dcard",
        "ACE交易所 詐騙 Dcard",
        "metamask詐騙dcard",
        "網 路 交友詐騙 Dcard",
        "幣安詐騙dcard",
        "被動收入詐騙 Dcard",
        "購物"
    ],
    "幣安": [
        "幣安詐騙",
        "幣安交易所",
        "幣安倒閉",
        "幣安台灣",
        "幣安ptt",
        "幣安安全嗎",
        "币安官网",
        "幣安教學",
        "詐騙",
        "交易 所"
    ],
    "幣安 賺幣 PTT": [
        "幣安活存dcard",
        "幣安活存ptt",
        "穩定幣ptt",
        "usdt定存ptt",
        "幣安 理財",
        "穩定幣利息 PTT",
        "幣安 Staking",
        "BUSD 幣 PTT"
    ],
    "幣安實體店面": [
        "   幣安新幣上市時間    ",
        "   幣安詐騙    ",
        "   幣安最新消息    ",
        "   幣安新幣上架    ",
        "   幣安上幣公告    ",
        "   幣安台灣    ",
        "   幣安官網    ",
        "   幣安c2c詐騙    "
    ],
    "幣安愛情詐騙": [
        "幣安詐騙交友",
        "usdt愛情詐騙",
        "ig幣安詐騙",
        "幣安詐騙香港",
        "交友軟體usdt詐騙",
        "幣安詐騙dcard",
        "usdt詐騙手法",
        "trust wallet詐騙ptt",
        "購物"
    ],
    "幣安詐騙dcard": [
        "幣安詐騙交友",
        "幣安愛情詐騙",
        "usdt詐騙dcard",
        "幣安dcard",
        "幣安安全嗎",
        "虛擬貨幣詐騙 交友 Dcard",
        "幣安交易所",
        "幣安ptt",
        "購物"
    ],
    "平台": [
        "平台英文",
        "平台解釋",
        "平臺平台",
        "平台還是平臺",
        "親師生平台",
        "網路平台意思",
        "系統平台",
        "親師生平台登入"
    ],
    "手機挖比特幣": [
        "手機挖比特幣app",
        "手機挖礦以太幣",
        "手機挖礦ptt",
        "手機挖礦風險",
        "手機挖礦app",
        "手機挖礦詐騙",
        "iphone挖礦app",
        "手機 挖 礦 收益"
    ],
    "投資詐騙錢拿的回來嗎": [
        "   詐騙拿回錢的機率ptt    ",
        "   被詐騙錢拿的回來嗎dcard    ",
        "   被詐騙拿回錢的機率    ",
        "   虛擬貨幣詐騙錢拿的回來嗎    ",
        "   被詐騙報警有用嗎dcard    ",
        "   蝦皮 詐騙 錢拿的回來嗎    ",
        "   被詐騙報警有用嗎    ",
        "   被詐騙拿回錢的機率香港    ",
        "購物"
    ],
    "挖礦合法嗎": [
        "挖礦賺錢原理",
        "挖礦詐騙",
        "挖礦電費",
        "挖礦風險",
        "免費挖礦",
        "挖礦機",
        "手機挖礦",
        "比特幣挖礦成本"
    ],
    "挖礦賺錢原理": [
        "挖礦詐騙",
        "挖礦賺錢ptt",
        "虛擬貨幣挖礦原理",
        "挖礦合法嗎",
        "挖礦風險",
        "比特幣挖礦成本",
        "顯卡挖礦原理",
        "挖礦電費"
    ],
    "新台幣匯率": [
        "新台幣匯率走勢",
        "美金台幣匯率",
        "美元匯率",
        "人民幣匯率",
        "匯率查詢",
        "台灣銀行匯率",
        "台幣汇率人民币",
        "今日台幣匯率走勢",
        "財經",
        "走勢"
    ],
    "東森購物": [
        "東森購物商品",
        "東森購物電話0800",
        "東森購物客服",
        "東森購物會員登入",
        "東森電視購物查詢",
        "東森購物吳宗憲",
        "東森購物直播47",
        "東森購物型錄"
    ],
    "比特幣 台灣銀行": [
        "比特幣台灣交易所",
        "比特幣台灣合法",
        "7-11買比特幣",
        "比特幣自動櫃員機地點",
        "台灣比特幣atm機",
        "比特幣atm領錢",
        "比特幣atm教學",
        "買比特幣要多少錢"
    ],
    "比特幣 當沖 PTT": [
        "比特幣致富 PTT",
        "幣圈 一天 人間十年 ptt",
        "比特幣賺錢 PTT",
        "比特幣 賠錢 PTT",
        "加密貨幣詐騙 PTT",
        "虛擬貨幣 套利 PTT",
        "加密貨幣投資 PTT",
        "Nicky 帶你飛 ptt",
        "購物"
    ],
    "比特幣 自動 交易 ptt": [
        "比特幣致富 PTT",
        "比特幣 當沖 PTT",
        "比特幣 賠錢 PTT",
        "SOL幣 PTT",
        "以太幣 PTT",
        "幣安 理財 PTT",
        "炒幣 PTT",
        "幣安 賺幣 PTT",
        "購物"
    ],
    "比特幣 賠錢 PTT": [
        "挖 礦 是什麼 PTT",
        "挖 礦 電費 PTT",
        "挖 礦 顯卡 PTT"
    ],
    "比特幣 賺錢 Dcard": [
        "虛擬貨幣慘賠dcard",
        "加密貨幣入門dcard",
        "虛擬貨幣心得ptt",
        "虛擬貨幣入門ptt",
        "虛擬貨幣被動收入dcard",
        "股票跟虛擬貨幣dcard",
        "加密貨幣dcard",
        "比特幣怎麼買dcard"
    ],
    "比特幣 開戶 ptt": [
        "虛擬貨幣入門dcard",
        "比特幣交易平台推薦 PTT",
        "比特幣換現金 ptt",
        "加密貨幣賺錢ptt",
        "比特幣怎麼玩 ptt",
        "買比特幣 PTT",
        "比特幣怎麼買 台灣",
        "幣安跟單教學",
        "購物"
    ],
    "比特幣10年前價格": [
        "比特幣最早價格",
        "比特幣歷史最低價格",
        "比特幣10年走勢圖",
        "比特幣十年走勢",
        "比特幣最低價格",
        "比特幣歷史價格走勢",
        "比特幣歷年價格",
        "比特幣歷史高位"
    ],
    "比特幣10年走勢圖": [
        "比特幣歷史價格走勢",
        "比特幣歷史最低價格",
        "比特幣歷史高位",
        "比特幣歷史最高價",
        "比特幣最低價格",
        "比特幣走勢圖",
        "比特幣歷年價格",
        "比特幣最早價格",
        "購物"
    ],
    "比特幣2024預測": [
        "比特幣走勢預測2024",
        "比特幣還可以買嗎",
        "比特幣走勢預測2023",
        "比特幣新聞即時",
        "比特幣走勢圖",
        "比特幣未來價格",
        "比特幣走勢分析",
        "虛擬貨幣未來趨勢"
    ],
    "比特幣atm教學": [
        "比特幣atm領錢",
        "bitcoin atm台灣",
        "比特幣自動櫃員機地點",
        "比特幣atm機",
        "比特幣atm手續費",
        "比特幣atm台北",
        "比特幣atm地圖",
        "比特幣atm詐騙"
    ],
    "比特幣dcard": [
        "比特幣入門dcard",
        "虛擬貨幣慘賠dcard",
        "比特幣ptt",
        "比特幣怎麼買dcard",
        "比特幣怎麼玩",
        "比特幣價格",
        "比特幣",
        "幣安",
        "購物"
    ],
    "比特幣etf代號": [],
    "比特幣etf台灣": [
        "台灣比特幣etf",
        "比特幣etf有哪些",
        "比特幣etf代號",
        "比特幣etf推薦",
        "比特幣etf怎麼買",
        "比特幣etf比較",
        "比特幣etf走勢",
        "比特幣etf ptt",
        "購物"
    ],
    "比特幣etf怎麼買": [],
    "比特幣etf推薦": [],
    "比特幣etf比較": [],
    "比特幣etf美股": [],
    "比特幣etf購買": [],
    "比特幣etf走勢": [
        "比特幣10年走勢",
        "比特幣走勢預測",
        "比特幣價格走勢",
        "比特幣歷史價格走勢",
        "比特幣現貨etf",
        "比特幣走勢圖",
        "比特幣etf怎麼買",
        "bitcoin etf美股",
        "購物"
    ],
    "比特幣ptt": [
        "比特幣致富ptt",
        "比特幣dcard",
        "比特幣崩盤ptt",
        "以太幣ptt",
        "幣圈入門ptt",
        "sol幣ptt",
        "比特幣購買 PTT",
        "虛擬貨幣破產ptt",
        "購物"
    ],
    "比特幣一顆多少台幣": [
        "1000比特幣等於台幣多少",
        "一比特幣等於多少美金",
        "5000台幣比特幣",
        "一個比特幣多少錢",
        "1比特幣挖多久",
        "比特幣換現金",
        "比特幣價格",
        "比特幣換算美金"
    ],
    "比特幣交易平台推薦 PTT": [
        "虛擬貨幣交易所dcard",
        "台灣三大交易所",
        "比特幣 開戶 ptt",
        "max交易所ptt",
        "買比特幣ptt",
        "比特幣怎麼玩 ptt",
        "weex交易所ptt",
        "買比特幣 平台"
    ],
    "比特幣交易平台推薦ptt": [
        "虛擬貨幣交易所dcard",
        "台灣三大交易所",
        "比特幣 開戶 ptt",
        "max交易所ptt",
        "買比特幣ptt",
        "比特幣怎麼玩 ptt",
        "weex交易所ptt",
        "買比特幣 平台"
    ],
    "比特幣交易平台推薦香港": [
        "香港比特幣倒閉",
        "香港虛擬貨幣交易所排名",
        "香港比特幣交易平台",
        "比特幣香港合法",
        "香港合法虛擬貨幣交易平台",
        "香港虛擬貨幣交易所牌照",
        "香港加密貨幣平台",
        "bitcoin換現金香港"
    ],
    "比特幣價格 PTT": [
        "比特幣致富 PTT",
        "比特幣dcard",
        "比特幣 PTT",
        "以太幣 PTT",
        "比特幣 大 跌 PTT",
        "比特幣購買 PTT",
        "炒幣 PTT",
        "幣圈 投資 ptt"
    ],
    "比特幣入門dcard": [
        "虛擬貨幣慘賠dcard",
        "比特幣怎麼買dcard",
        "幣圈新手 Dcard",
        "虛擬貨幣交易所 Dcard",
        "比特幣ptt",
        "比特幣怎麼玩",
        "比特幣價格",
        "幣安",
        "購物"
    ],
    "比特幣十年走勢": [
        "比特幣歷史價格走勢",
        "比特幣10年走勢圖",
        "比特幣歷年價格",
        "比特幣歷史最低價格",
        "比特幣最低價格",
        "比特幣歷史高位",
        "比特幣歷史最高價",
        "比特幣價格",
        "圖"
    ],
    "比特幣可以買什麼": [
        "比特幣可以換現金嗎",
        "比特幣支付台灣",
        "比特幣可以幹嘛",
        "比特幣怎麼買dcard",
        "7-11買比特幣",
        "比特幣怎麼買台灣",
        "比特幣怎麼買賣",
        "比特幣可以買嗎"
    ],
    "比特幣台幣走勢": [
        "1000比特幣等於台幣多少",
        "比特幣走勢圖",
        "比特幣走勢",
        "比特幣10年走勢",
        "5000台幣比特幣",
        "比特幣美金",
        "一比特幣等於多少美金",
        "比特幣價格美元"
    ],
    "比特幣台灣交易所": [
        "比特幣台灣銀行",
        "台灣虛擬貨幣交易所排名",
        "比特幣台灣合法",
        "台灣合法虛擬貨幣交易所",
        "台灣虛擬貨幣交易所倒閉",
        "比特幣交易平台推薦",
        "虛擬貨幣交易所詐騙",
        "台灣虛擬貨幣交易所ptt"
    ],
    "比特幣台灣合法": [
        "比特幣台灣交易所",
        "比特幣台灣銀行",
        "比特幣合法國家",
        "台灣虛擬貨幣違法",
        "台灣合法虛擬貨幣交易所",
        "承認比特幣的國家",
        "台灣虛擬貨幣法規",
        "虛擬貨幣合法國家"
    ],
    "比特幣台灣合法嗎": [
        "比特幣台灣銀行",
        "比特幣台灣交易所",
        "台灣合法虛擬貨幣交易所",
        "虛擬貨幣合法國家",
        "台灣虛擬貨幣違法",
        "承認比特幣的國家",
        "比特幣合法國家",
        "台灣虛擬貨幣法規"
    ],
    "比特幣投資ptt": [
        "比特幣致富 PTT",
        "比特幣dcard",
        "虛擬貨幣 破產 PTT",
        "虛擬貨幣入門ptt",
        "比特幣價格 PTT",
        "比特幣 大 跌 PTT",
        "以太幣 PTT",
        "虛擬貨幣 套利 PTT"
    ],
    "比特幣投資平台": [
        "比特幣交易平台推薦ptt",
        "比特幣交易平台推薦",
        "台灣合法虛擬貨幣交易所",
        "虛擬貨幣交易所詐騙",
        "台灣比特幣交易平台",
        "比特幣台灣合法",
        "比特幣哪裡買",
        "加密貨幣交易所"
    ],
    "比特幣挖礦原理ptt": [
        "挖 礦 是什麼 PTT",
        "挖 礦 教學 PTT",
        "2023挖礦ptt",
        "礦機 PTT",
        "挖 礦 顯卡 PTT",
        "小礦工挖挖礦ptt",
        "挖 礦 電費 PTT",
        "重新執行搜尋並顯示所有結果",
        "購物"
    ],
    "比特幣挖礦成本": [
        "比特幣挖礦成本計算",
        "比特幣挖礦原理",
        "比特幣關機價",
        "挖礦一個月電費",
        "比特幣挖礦機價格",
        "比特幣電費",
        "比特幣 挖 礦 算力",
        "挖礦 收益"
    ],
    "比特幣挖礦教學": [
        "1比特幣挖多久",
        "比特幣挖礦程式下載",
        "比特幣挖礦程式",
        "挖礦風險",
        "手機挖礦",
        "比特幣挖礦網站",
        "免費挖礦",
        "比特幣挖礦機"
    ],
    "比特幣挖礦機": [
        "挖礦機詐騙",
        "比特幣挖礦成本",
        "比特幣挖礦原理",
        "比特幣礦機收益",
        "1比特幣挖多久",
        "比特幣挖礦機價格",
        "挖礦機是什麼",
        "免費挖礦"
    ],
    "比特幣挖礦程式下載": [
        "手機挖礦程式",
        "乙太幣挖礦程式",
        "比特幣挖礦教學",
        "挖礦程式是什麼",
        "泰達幣挖礦程式",
        "抓比特幣程式",
        "挖礦程式偵測",
        "挖礦軟體推薦ptt",
        "購物"
    ],
    "比特幣換台幣ptt": [
        "比特幣dcard",
        "比特幣 PTT",
        "以太幣 PTT",
        "購物"
    ],
    "比特幣換台幣手續費": [
        "虛擬貨幣出金ptt",
        "比特幣換現金台灣",
        "虛擬貨幣換台幣",
        "如何在幣安出金換成台幣",
        "幣安提現 銀行",
        "虛擬貨幣大額出金",
        "幣安提現失敗",
        "trc20手續費"
    ],
    "比特幣換現金ptt": [],
    "比特幣換現金台灣": [
        "比特幣換現金ptt",
        "比特幣換台幣",
        "幣安提現 銀行",
        "虛擬貨幣換台幣",
        "虛擬貨幣出金繳稅",
        "如何在幣安出金換成台幣",
        "虛擬貨幣大額出金",
        "虛擬貨幣出金ptt"
    ],
    "比特幣換算美金": [
        "比特幣換算台幣",
        "一塊比特幣等於多少美金",
        "比特幣美金走勢",
        "一顆比特幣價格",
        "1000比特幣等於台幣多少",
        "比特幣價格美元",
        "以太幣美金",
        "比特幣換匯",
        "財經",
        "購物"
    ],
    "比特幣新聞即時": [
        "虛擬貨幣即時新聞",
        "比特幣新聞狂人",
        "幣圈最新消息",
        "比特幣暴跌",
        "台灣比特幣新聞",
        "比特幣即時走勢",
        "比特幣價格",
        "比特幣走勢預測"
    ],
    "比特幣新聞狂人": [
        "幣圈最新消息",
        "比特幣新聞即時",
        "狂人反指標",
        "比特幣論壇",
        "鏈新聞",
        "比特幣走勢",
        "狂人說趨勢ptt",
        "桑幣",
        "購物"
    ],
    "比特幣暴跌": [
        "比特幣走勢",
        "比特幣走勢圖",
        "比特幣爆倉意思",
        "比特幣價格",
        "比特幣怎麼玩",
        "比特幣美金",
        "比特幣減半",
        "比特幣etf"
    ],
    "比特幣最低價格": [
        "比特幣10年前價格",
        "比特幣最早價格",
        "比特幣十年走勢",
        "比特幣歷史價格",
        "比特幣價格美元",
        "比特幣歷史價格走勢",
        "比特幣歷年價格",
        "比特幣價格走勢"
    ],
    "比特幣最早價格": [
        "比特幣歷史最低價格",
        "比特幣10年前價格",
        "比特幣歷史價格",
        "比特幣最低價格",
        "比特幣發行價格",
        "比特幣歷年價格",
        "比特幣歷史高位",
        "比特幣十年走勢"
    ],
    "比特幣概念股3443": [
        "台灣比特幣概念股",
        "真正的比特幣概念股",
        "比特幣概念股 PTT",
        "台灣有哪些虛擬貨幣概念股",
        "比特幣 股票代號",
        "美國比特幣概念股",
        "比特幣挖礦概念股",
        "台股比特幣etf"
    ],
    "比特幣概念股ptt": [
        "比特幣概念股3443",
        "真正 的比特幣概念股",
        "台灣比特幣概念股",
        "比特幣概念股美股",
        "比特幣 概念股 龍頭",
        "比特幣ETF 概念股",
        "台灣有哪些虛擬貨幣概念股",
        "以太 幣概念股",
        "購物"
    ],
    "比特幣概念股台股": [
        "真正的比特幣概念股",
        "比特幣概念股ptt",
        "比特幣股票代號",
        "比特幣股票有哪些",
        "比特幣概念股美股",
        "台灣有哪些虛擬貨幣概念股",
        "比特幣概念股3443",
        "台股比特幣etf"
    ],
    "比特幣概念股美股": [
        "真正的比特幣概念股",
        "比特幣概念股ptt",
        "比特幣股票代號",
        "台灣比特幣概念股",
        "加密貨幣概念股美股",
        "台灣有哪些虛擬貨幣概念股",
        "比特幣美股",
        "比特幣 概念股 龍頭",
        "購物"
    ],
    "比特幣歷史價格": [
        "比特幣十年走勢",
        "比特幣歷史最低價格",
        "比特幣歷年價格",
        "比特幣歷史高位",
        "比特幣歷史最高價",
        "比特幣最早價格",
        "比特幣最低價格",
        "比特幣歷史走勢"
    ],
    "比特幣歷史最低價格": [
        "比特幣十年走勢",
        "比特幣歷史價格走勢",
        "比特幣最早價格",
        "比特幣歷史新高",
        "比特幣歷史最高價",
        "比特幣發行價格",
        "比特幣價格",
        "比特幣最初價格"
    ],
    "比特幣歷史最高價": [
        "比特幣歷史價格走勢",
        "比特幣十年走勢",
        "比特幣歷史新高",
        "比特幣最早價格",
        "比特幣10年前價格",
        "比特幣最高點",
        "比特幣發行價格",
        "比特幣價格"
    ],
    "比特幣歷史高位": [
        "比特幣歷史最高價",
        "比特幣十年走勢",
        "比特幣歷史價格",
        "比特幣歷年價格",
        "比特幣最低價格",
        "比特幣最早價格",
        "比特幣歷史價格走勢",
        "比特幣10年前價格"
    ],
    "比特幣歷年價格": [
        "比特幣十年走勢",
        "比特幣10年前價格",
        "比特幣歷史高位",
        "比特幣十年走勢圖",
        "比特幣歷史最高價格",
        "比特幣價格",
        "比特幣發行價格",
        "比特幣最低價格"
    ],
    "比特幣缺點": [
        "比特幣投資詐騙",
        "投資比特幣安全嗎",
        "比特幣台灣合法嗎",
        "比特幣優缺點",
        "比特幣可以換現金嗎",
        "比特幣投資平台",
        "虛擬貨幣優缺點",
        "比特幣走勢"
    ],
    "比特幣股票代號": [
        "比特幣股票有哪些",
        "比特幣美股代號",
        "比特幣10年走勢",
        "真正的比特幣概念股",
        "比特幣價格美元",
        "比特幣價格",
        "比特幣走勢預測",
        "比特幣etf"
    ],
    "比特幣股票有哪些": [
        "比特幣股票代號",
        "比特幣概念股3443",
        "比特幣etf台灣",
        "比特幣概念股美股",
        "比特幣etf概念股",
        "比特幣概念股是什麼",
        "比特幣概念股ptt",
        "比特幣美股"
    ],
    "比特幣自動櫃員機地點": [
        "台北比特幣提款機",
        "比特幣atm教學",
        "比特幣atm地圖",
        "比特幣atm詐騙",
        "比特幣atm機",
        "比特幣提款機台灣",
        "比特幣販賣機",
        "比特幣atm手續費"
    ],
    "比特幣致富 PTT": [
        "虛擬貨幣 致富 PTT",
        "虛擬貨幣 賺錢 PTT",
        "虛擬貨幣 套利 PTT",
        "虛擬貨幣 股票 PTT",
        "加密貨幣投資 PTT",
        "加密貨幣詐騙 PTT"
    ],
    "比特幣致富ptt": [
        "虛擬貨幣 致富 PTT",
        "虛擬貨幣 賺錢 PTT",
        "虛擬貨幣 套利 PTT",
        "虛擬貨幣 股票 PTT",
        "加密貨幣詐騙 PTT",
        "加密貨幣投資 PTT",
        "重新執行搜尋並顯示所有結果",
        "購物"
    ],
    "比特幣詐騙dcard": [
        "虛擬貨幣詐騙交友dcard",
        "虛擬貨幣詐騙dcard",
        "幣安詐騙dcard",
        "max交易所詐騙dcard",
        "ACE交易所 詐騙 Dcard",
        "usdt詐騙dcard",
        "網 路 交友詐騙 Dcard",
        "metamask詐騙dcard",
        "購物"
    ],
    "比特幣詐騙手法": [
        "比特幣詐騙交友",
        "虛擬貨幣詐騙交友",
        "比特幣詐騙平台",
        "line比特幣詐騙",
        "比特幣詐騙ptt",
        "虛擬貨幣詐騙錢拿的回來嗎",
        "比特幣詐騙dcard",
        "虛擬貨幣詐騙案例"
    ],
    "比特幣詐騙新聞": [],
    "比特幣賺錢 PTT": [
        "比特幣致富 PTT",
        "比特幣價格 PTT",
        "SOL幣 PTT",
        "幣安 賺幣 PTT",
        "以太幣 PTT",
        "比特幣 當沖 PTT",
        "比特幣 賠錢 PTT",
        "比特幣 開戶 ptt",
        "購物"
    ],
    "比特幣購買 PTT": [
        "比特幣交易平台推薦ptt",
        "比特幣怎麼買 台灣",
        "比特幣 最少 買多少",
        "比特幣怎麼玩 ptt",
        "全家買比特幣 PTT",
        "比特幣致富 PTT",
        "SOL幣 PTT",
        "比特幣 開戶 ptt",
        "購物"
    ],
    "比特幣走勢分析": [
        "比特幣10年走勢",
        "比特幣走勢圖",
        "比特幣走勢預測",
        "比特幣歷史價格走勢",
        "比特幣概念股",
        "乙太幣走勢",
        "比特幣怎麼玩",
        "比特幣股票有哪些"
    ],
    "比特幣走勢預測2023": [
        "比特幣走勢預測2024",
        "比特幣新聞即時",
        "比特幣還可以買嗎",
        "比特幣2024預測",
        "比特幣走勢圖",
        "比特幣價格",
        "比特幣走勢分析",
        "比特幣未來"
    ],
    "比特幣走勢預測2024": [
        "比特幣2024預測",
        "比特幣還可以買嗎",
        "比特幣走勢圖",
        "比特幣走勢分析",
        "比特幣走勢預測2023",
        "比特幣新聞即時",
        "比特幣歷史價格走勢",
        "比特幣10年走勢"
    ],
    "比特幣還可以買嗎": [],
    "比特幣開戶台灣": [
        "比特幣台灣銀行",
        "台灣比特幣交易平台",
        "7-11買比特幣",
        "比特幣怎麼買dcard",
        "比特幣帳戶申請",
        "買比特幣詐騙",
        "比特幣台灣合法",
        "比特幣怎麼買賣"
    ],
    "比特幣香港合法": [
        "香港合法虛擬貨幣交易平台",
        "香港虛擬貨幣監管",
        "香港加密货币交易所",
        "binance香港禁止",
        "幣安香港限制",
        "香港虛擬貨幣交易所排名",
        "香港数字货币交易所牌照",
        "加密貨幣香港合法"
    ],
    "泰達幣詐騙 PTT": [
        "泰達幣交易所",
        "JPEX 詐騙 PTT",
        "虛擬貨幣 心得 PTT",
        "泰達幣挖礦",
        "信用卡 買幣 PTT",
        "以太幣 PTT",
        "幣安ptt",
        "狗 狗幣 PTT"
    ],
    "火幣詐騙 PTT": [
        "火幣詐騙手法",
        "火幣安全嗎",
        "火幣ptt",
        "以太幣詐騙PTT",
        "火幣帳號出租",
        "huobi詐騙",
        "比特幣 詐騙 PTT",
        "火幣交易所"
    ],
    "美元人民币": [
        "美元兌人民幣計算",
        "人民幣對美元匯率今天",
        "美元兌人民幣走勢",
        "人民幣兌美元匯率歷史走勢",
        "人民幣美元匯率走勢10年",
        "人民幣台幣",
        "人民幣美金即時匯率",
        "美元兌人民幣離岸",
        "財經"
    ],
    "美元兌台幣未來走勢": [
        "下半年美元走勢",
        "台幣兌美元走勢圖",
        "今日台幣匯率走勢",
        "美元未來十年走勢",
        "2024台幣兌美元走勢預測",
        "2024美元走勢預測",
        "現在適合買美金嗎",
        "美元匯率",
        "購物"
    ],
    "美元兌日圓": [],
    "美元匯率": [
        "美元匯率走勢",
        "日幣匯率",
        "美元匯率台幣",
        "澳幣匯率",
        "人民幣匯率",
        "歐元匯率",
        "美元兌台幣未來走勢",
        "美元匯率走勢10年",
        "財經",
        "走勢"
    ],
    "美元匯率走勢圖": [
        "美金匯率走勢預測",
        "美元匯率走勢10年",
        "美元兌台幣未來走勢",
        "台幣美金匯率走勢",
        "今日台幣匯率走勢",
        "今日台幣匯率走勢圖",
        "下半年美元走勢",
        "美元匯率走勢5年",
        "購物"
    ],
    "美元台幣": [
        "美元兌台幣未來走勢",
        "美元指數",
        "美元台幣匯率",
        "1美金換台幣",
        "美元兌台幣走勢",
        "美元匯率",
        "今日台幣匯率走勢",
        "美元兌日圓",
        "財經"
    ],
    "美元指數": [
        "美元指數是什麼",
        "美元匯率",
        "美元指數走勢",
        "美元指數台幣匯率",
        "美元指數走勢圖",
        "美元指數越高",
        "美元指數走勢十年",
        "美元兌台幣"
    ],
    "美元走勢": [
        "美元兌台幣未來走勢",
        "美元走勢圖",
        "美元走勢十年",
        "下半年美元走勢",
        "美金匯率走勢預測",
        "美元匯率",
        "台幣兌美元走勢圖",
        "美元台幣"
    ],
    "美金台幣匯率": [
        "美金台幣走勢",
        "1美金換台幣",
        "美金匯率",
        "台灣銀行美金匯率",
        "美金匯率走勢",
        "日幣匯率",
        "美金匯率走勢預測",
        "美元兌台幣未來走勢",
        "財經"
    ],
    "美金台幣走勢": [
        "美元兌台幣未來走勢",
        "1美金換台幣",
        "美金匯率走勢預測",
        "今日台幣匯率走勢",
        "美金台幣匯率",
        "美金匯率走勢圖十年",
        "下半年美元走勢",
        "美元匯率走勢圖"
    ],
    "虛擬貨幣 看 盤 PTT": [
        "虛擬貨幣賠錢 PTT",
        "虛擬貨幣 心得 PTT",
        "虛擬貨幣 出 金 PTT",
        "虛擬貨幣現貨",
        "虛擬貨幣 套利 PTT",
        "虛擬貨幣槓桿ptt",
        "虛擬貨幣分析",
        "合約交易 PTT",
        "購物"
    ],
    "虛擬貨幣交易平台": [
        "虛擬貨幣交易所詐騙",
        "虛擬貨幣交易平台推薦",
        "台灣虛擬貨幣交易所排名",
        "虛擬貨幣交易所台灣",
        "台灣合法虛擬貨幣交易所",
        "台灣虛擬貨幣交易所倒閉",
        "虛擬貨幣怎麼玩",
        "數字貨幣交易平台詐騙",
        "推薦"
    ],
    "虛擬貨幣交易所詐騙": [],
    "虛擬貨幣即時新聞": [
        "國際新聞虛擬貨幣",
        "幣圈最新消息",
        "比特幣新聞即時",
        "虛擬貨幣新聞app",
        "台灣加密貨幣新聞",
        "虛擬貨幣大跌",
        "幣圈新聞",
        "虛擬貨幣現況",
        "購物"
    ],
    "虛擬貨幣實體店面": [
        "虛擬貨幣實體店面台北",
        "台中虛擬貨幣實體店面",
        "比特幣實體店面",
        "台灣加密貨幣實體店",
        "台北usdt實體店",
        "高雄虛擬貨幣實體店面",
        "台南虛擬貨幣實體店面",
        "嘉義虛擬貨幣實體店面"
    ],
    "虛擬貨幣帳戶凍結": [
        "虛擬貨幣帳戶凍結原因",
        "usdt帳戶凍結",
        "虛擬貨幣詐騙錢拿的回來嗎",
        "交易所 凍結帳戶",
        "比特幣帳戶被凍結",
        "幣商 警示帳戶",
        "MAX 交易所 凍結",
        "USDT 詐騙手法"
    ],
    "虛擬貨幣慘賠dcard": [
        "虛擬貨幣慘賠ptt",
        "虛擬貨幣dcard",
        "虛擬貨幣入門ptt",
        "股票 跟 虛擬貨幣 Dcard",
        "合約 賠 光",
        "比特幣",
        "秒合約 Dcard",
        "P1trader Dcard"
    ],
    "虛擬貨幣技術分析PTT": [
        "虛擬貨幣技術分析書",
        "虛擬貨幣 賺錢 PTT",
        "虛擬貨幣技術分析教學",
        "虛擬貨幣 看 盤 PTT",
        "比特幣致富 PTT",
        "技術分析 教學 PTT",
        "技術分析入門",
        "虛擬貨幣合約 PTT",
        "購物"
    ],
    "虛擬貨幣挖礦原理": [
        "挖礦賺錢原理",
        "挖礦合法嗎",
        "比特幣挖礦原理ptt",
        "挖礦詐騙",
        "以太幣挖礦原理",
        "1比特幣挖多久",
        "比特幣挖礦成本",
        "挖礦程式"
    ],
    "虛擬貨幣洗錢ptt": [
        "usdt洗錢",
        "虛擬貨幣 破產 PTT",
        "被懷疑洗錢ptt",
        "虛擬貨幣 股票 PTT",
        "虛擬貨幣 套利 PTT",
        "加密貨幣詐騙 PTT",
        "比特幣致富 PTT",
        "加密貨幣投資 PTT",
        "購物"
    ],
    "虛擬貨幣詐騙dcard": [
        "虛擬貨幣詐騙交友dcard",
        "usdt詐騙dcard",
        "虛擬貨幣詐騙ptt",
        "max交易所詐騙dcard",
        "虛擬貨幣詐騙錢拿的回來嗎",
        "虛擬貨幣詐騙藝人",
        "虛擬貨幣dcard",
        "okx詐騙手法"
    ],
    "虛擬貨幣詐騙ptt": [
        "虛擬貨幣詐騙dcard",
        "虛擬貨幣詐騙交友",
        "虛擬貨幣洗錢PTT",
        "usdt詐騙ptt",
        "虛擬貨幣 工作 PTT",
        "火幣詐騙 PTT",
        "外匯詐騙PTT",
        "以太幣詐騙PTT"
    ],
    "虛擬貨幣詐騙案例": [
        "虛擬貨幣詐騙交友",
        "虛擬貨幣詐騙錢拿的回來嗎",
        "虛擬貨幣詐騙dcard",
        "比特幣詐騙手法",
        "虛擬貨幣詐騙ptt",
        "比特幣詐騙交友",
        "期貨詐騙手法",
        "詐騙交易所查詢"
    ],
    "虛擬貨幣詐騙自救": [
        "詐騙拿回錢的機率",
        "虛擬貨幣詐騙ptt",
        "虛擬貨幣詐騙dcard",
        "虛擬貨幣詐騙交友",
        "台灣虛擬貨幣詐騙",
        "MAX 交易所詐騙手法",
        "被詐騙錢拿的回來嗎dcard",
        "虛擬貨幣詐騙 破案"
    ],
    "蝦皮購物": [
        "蝦皮購物網站",
        "蝦皮購物台灣",
        "蝦皮購物app",
        "蝦皮網頁版登入",
        "蝦皮登入",
        "蝦皮購物app下載",
        "蝦皮店到店",
        "蝦皮網頁版手機",
        "購物",
        "網站"
    ],
    "蝦皮購物網站": [
        "蝦皮網頁版登入",
        "蝦皮電腦版網頁",
        "蝦皮網頁版手機",
        "蝦皮購物app",
        "蝦皮店到店",
        "蝦皮登入",
        "蝦皮賣家中心",
        "蝦皮客服",
        "購物"
    ],
    "被詐騙錢拿的回來嗎dcard": [
        "詐騙拿回錢的機率ptt",
        "被詐騙報警有用嗎 Dcard",
        "被詐騙拿回錢的機率",
        "被詐騙怎麼辦dcard",
        "被詐騙集團 騙 錢 Dcard",
        "詐騙開庭dcard",
        "賣 貨 便詐騙 錢拿的回來嗎",
        "下午3點半到晚上12點 被詐騙的錢 可拿回來",
        "購物"
    ],
    "詐騙 集團": [
        "詐騙集團手法",
        "詐騙集團英文",
        "詐騙集團的下場",
        "詐騙集團最新消息",
        "詐騙集團感情",
        "詐騙集團密語",
        "詐騙集團虛擬貨幣",
        "詐騙集團最新被捕消息"
    ],
    "詐騙拿回錢的機率ptt": [
        "詐騙拿回錢的機率dcard",
        "下午3點半到晚上12點 被詐騙的錢 可拿回來",
        "詐騙的錢拿的回來嗎",
        "追回被詐騙的錢",
        "詐騙拿回錢ptt",
        "詐騙案件處理時間ptt",
        "被詐騙報警有用嗎dcard",
        "錢被騙想不開"
    ],
    "財經google": [
        "google財經app",
        "google財經桌面",
        "google finance投資組合",
        "google財經找不到",
        "google finance美股",
        "google finance台股",
        "google財經捷徑",
        "Google Finance"
    ],
    "財經新聞": [
        "今日最新財經新聞",
        "財經新聞快報",
        "財經新聞重點",
        "股市財經新聞",
        "每日財經新聞",
        "今日財經新聞頭條",
        "財經新聞線上看",
        "即時國際財經新聞"
    ],
    "財經日報": [
        "工商時報",
        "經濟日報頭條",
        "經濟日報要聞",
        "今日最新財經新聞",
        "經濟日報即時新聞",
        "經濟日報線上看",
        "經濟日報免費訂閱",
        "經濟日報電子報紙",
        "要聞"
    ],
    "財經是什麼": [
        "財經系出路薪水",
        "財經系學什麼",
        "財經系大學排名",
        "財經系在幹嘛",
        "金融是做什麼的",
        "財經系出路",
        "財經學群人格特質",
        "金融業是什麼"
    ],
    "財經系": [
        "   財經系大學排名    ",
        "   財經系出路    ",
        "   財經系學什麼    ",
        "   財經系出路薪水    ",
        "   財經系介紹    ",
        "   財經系學校    ",
        "   財經系在幹嘛    ",
        "   財經系英文    "
    ],
    "財經網站": [
        "鉅亨網",
        "財經網站排名",
        "財經m平方創辦人",
        "財經m平方缺點",
        "玩股網",
        "玩股網選股",
        "財經m平方dcard",
        "玩股網app",
        "購物"
    ],
    "財經股市": [
        "財經新聞快報",
        "今日股市大跌原因",
        "今日最新財經新聞",
        "股市財經新聞",
        "今日股市行情",
        "每日財經新聞",
        "股市即時新聞app",
        "台灣財經新聞",
        "購物"
    ],
    "財經英文": [
        "財經英文單字",
        "財經英文新聞",
        "財經系英文",
        "財經英文雜誌",
        "財金系英文",
        "財金英文",
        "經濟英文",
        "理財英文"
    ],
    "買bitcoin lihkg": [
        "Bitcoin",
        "Binance",
        "重新執行搜尋並顯示所有結果"
    ],
    "買bitcoin犯法": [
        "比特幣台灣交易所",
        "比特幣台灣銀行",
        "台灣合法虛擬貨幣交易所",
        "比特幣合法國家",
        "虛擬貨幣洗錢防制法",
        "虛擬貨幣合法國家",
        "台灣虛擬貨幣詐騙",
        "虛擬貨幣私下交易"
    ],
    "買比特幣平台": [
        "比特幣交易平台推薦ptt",
        "台灣比特幣交易平台",
        "虛擬貨幣交易所詐騙",
        "比特幣台灣銀行",
        "比特幣台灣合法",
        "比特幣怎麼買dcard",
        "比特幣交易所",
        "7-11買比特幣"
    ],
    "買比特幣詐騙": [],
    "賣比特幣": [
        "7-11買比特幣",
        "比特幣怎麼買台灣",
        "比特幣價格",
        "比特幣怎麼買dcard",
        "幣託詐騙",
        "幣托安全嗎",
        "幣安",
        "BitoPro"
    ],
    "購買比特幣流程": [
        "7-11買比特幣",
        "買比特幣要多少錢",
        "比特幣怎麼買台灣",
        "購買比特幣ptt",
        "比特幣怎麼買dcard",
        "比特幣台灣銀行",
        "買bitcoin犯法",
        "比特幣怎麼買賣"
    ],
    "預測": [
        "預測英文",
        "預測lol",
        "預測意思",
        "預測分析",
        "預測分析例子",
        "預測模型方法",
        "預測未來",
        "預測方法"
    ],
    "香港比特幣倒閉": [
        "香港虛擬貨幣合法",
        "比特幣詐騙交友",
        "aax苦主",
        "香港虛擬貨幣交易平台",
        "aax倒閉",
        "香港加密貨幣交易所",
        "jpex事件懶人包",
        "aax苦主telegram"
    ],
    "香港比特幣提款機": [
        "比特幣自動櫃員機地點",
        "比特幣atm詐騙",
        "bitcoin atm提款",
        "比特幣atm機",
        "bitcoin換現金香港",
        "bitcoin atm香港手續費",
        "比特幣atm教學",
        "香港usdt atm"
    ],
    "香港虛擬貨幣交易所排名": [
        "香港虛擬貨幣合法",
        "香港数字货币交易所牌照",
        "香港加密貨幣交易所",
        "虛擬貨幣交易所詐騙",
        "台灣虛擬貨幣交易所排名",
        "全球交易所排名",
        "香港虛擬貨幣交易中心",
        "台灣合法虛擬貨幣交易所"
    ]
}